modernmetric/__init__.py
modernmetric/__main__.py
modernmetric/config.py
modernmetric/diff_process.py
modernmetric/fp.py
modernmetric/license.py
modernmetric/cls/__init__.py
modernmetric/cls/base.py
modernmetric/cls/base_calc.py
modernmetric/cls/base_stats.py
modernmetric/cls/modules.py
modernmetric/cls/calc/__init__.py
modernmetric/cls/calc/halstead.py
modernmetric/cls/calc/maintenance.py
modernmetric/cls/calc/pylint.py
modernmetric/cls/calc/tiobe.py
modernmetric/cls/importer/__init__.py
modernmetric/cls/importer/base.py
modernmetric/cls/importer/filtered.py
modernmetric/cls/importer/pick.py
modernmetric/cls/importer/mods/__init__.py
modernmetric/cls/importer/mods/csv.py
modernmetric/cls/importer/mods/json.py
modernmetric/cls/metric/__init__.py
modernmetric/cls/metric/comments.py
modernmetric/cls/metric/cyclomatic.py
modernmetric/cls/metric/fanout.py
modernmetric/cls/metric/loc.py
modernmetric/cls/metric/operands.py
modernmetric/cls/metric/operators.py
modernmetric/cls/stats/__init__.py
modernmetric/cls/stats/stats.py
modernmetric-1.5.8.dist-info/METADATA
modernmetric-1.5.8.dist-info/WHEEL
modernmetric-1.5.8.dist-info/entry_points.txt
modernmetric-1.5.8.dist-info/licenses/LICENSE
modernmetric-1.5.8.dist-info/RECORD
