Metadata-Version: 2.4
Name: modernmetric
Version: 1.5.8
Summary: Calculate code metrics in various languages
Project-URL: Homepage, https://github.com/verinfast/modernmetric
Project-URL: Bug Tracker, https://github.com/verinfast/modernmetric/issues
Project-URL: Source, https://github.com/verinfast/modernmetric
Author-email: Jason Nichols <github@verinfast.com>
License-Expression: CC-BY-NC-4.0
License-File: LICENSE
Classifier: Development Status :: 4 - Beta
Classifier: Environment :: Console
Classifier: Intended Audience :: Developers
Classifier: License :: Free for non-commercial use
Classifier: Natural Language :: English
Classifier: Operating System :: POSIX :: Linux
Classifier: Programming Language :: Python :: 3
Classifier: Programming Language :: Python :: 3 :: Only
Classifier: Programming Language :: Python :: 3.9
Classifier: Programming Language :: Python :: 3.10
Classifier: Programming Language :: Python :: 3.11
Classifier: Topic :: Software Development :: Quality Assurance
Requires-Python: >=3.9
Requires-Dist: cachehash~=1.1.0
Requires-Dist: chardet>=5.2.0
Requires-Dist: httpx[http2]~=0.28.1
Requires-Dist: pygments-tsx>=1.0.1
Requires-Dist: pygments>=2.15.1
Requires-Dist: pygount
Provides-Extra: dev
Requires-Dist: black>=24.1.1; extra == 'dev'
Requires-Dist: pytest; extra == 'dev'
Requires-Dist: pytest-cov; extra == 'dev'
